reporting_pool/__init__.py
reporting_pool/reporting_pool.py
reporting_pool-0.1.4.dist-info/LICENSE
reporting_pool-0.1.4.dist-info/METADATA
reporting_pool-0.1.4.dist-info/WHEEL
reporting_pool-0.1.4.dist-info/top_level.txt
reporting_pool-0.1.4.dist-info/RECORD
