Metadata-Version: 2.1
Name: reporting_pool
Version: 0.1.4
Summary: A wrapper around multiprocessing.Pool that keeps track of the completion and exceptions.
Author-email: Anton Sobinov <an.sobinov@gmail.com>
Project-URL: Homepage, https://github.com/nishbo/reporting_pool
Classifier: Programming Language :: Python :: 3
Classifier: License :: OSI Approved :: MIT License
Classifier: Operating System :: OS Independent
Classifier: Development Status :: 5 - Production/Stable
Classifier: Environment :: Console
Requires-Python: >=3.7
License-File: LICENSE
